ailia_voice/LICENSE_AILIA_EN.pdf
ailia_voice/LICENSE_AILIA_JA.pdf
ailia_voice/__init__.py
ailia_voice/linux/arm64-v8a/libailia_voice.so
ailia_voice/linux/x64/libailia_voice.so
ailia_voice/mac/libailia_voice.dylib
ailia_voice/windows/x64/ailia_voice.dll
ailia_voice-1.4.0.0.data/scripts/__init__.py
ailia_voice-1.4.0.0.dist-info/METADATA
ailia_voice-1.4.0.0.dist-info/WHEEL
ailia_voice-1.4.0.0.dist-info/top_level.txt
ailia_voice-1.4.0.0.dist-info/RECORD
