Metadata-Version: 2.4
Name: ailia_voice
Version: 1.4.0.0
Summary: ailia AI Voice
Home-page: https://ailia.ai/en/
Author: ailia Inc.
Author-email: contact@ailia.ai
License: https://ailia.ai/en/license/
Requires-Python: >3.6
Requires-Dist: ailia
Dynamic: author
Dynamic: author-email
Dynamic: description
Dynamic: description-content-type
Dynamic: home-page
Dynamic: license
Dynamic: requires-dist
Dynamic: requires-python
Dynamic: summary
